corella/__init__.py
corella/add_eventID_occurrences.py
corella/add_unique_IDs.py
corella/add_unique_occurrence_ids.py
corella/basisOfRecord_values.py
corella/bor_values.py
corella/check_abundance.py
corella/check_basisOfRecord.py
corella/check_collection.py
corella/check_coordinates.py
corella/check_data.py
corella/check_dataset.py
corella/check_datetime.py
corella/check_emof.py
corella/check_events.py
corella/check_individual_traits.py
corella/check_license.py
corella/check_locality.py
corella/check_multimedia.py
corella/check_observer.py
corella/check_occurrenceIDs.py
corella/check_occurrenceStatus.py
corella/check_occurrence_data.py
corella/check_occurrences.py
corella/check_scientificName.py
corella/check_taxonomy.py
corella/common_dictionaries.py
corella/common_functions.py
corella/countryCode_values.py
corella/event_terms.py
corella/future_functions.py
corella/generate_eventID_parentEventID.py
corella/get_dwc_noncompliant_terms.py
corella/occurrence_terms.py
corella/read_dwc_terms_links.py
corella/read_dwc_terms_list.py
corella/set_abundance.py
corella/set_collection.py
corella/set_coordinates.py
corella/set_datetime.py
corella/set_events.py
corella/set_individual_traits.py
corella/set_license.py
corella/set_locality.py
corella/set_multimedia.py
corella/set_observer.py
corella/set_occurrences.py
corella/set_scientific_name.py
corella/set_taxonomy.py
corella/suggest_workflow.py
corella/switch_check.py
corella/use_abundance.py
corella/use_coordinates.py
corella/use_datetime.py
corella/use_events.py
corella/use_locality.py
corella/use_multimedia.py
corella/use_occurrences.py
corella/use_scientific_name.py
corella/version.py
corella/wikipedia_country_codes.csv
corella_python-0.1.5.dist-info/METADATA
corella_python-0.1.5.dist-info/WHEEL
corella_python-0.1.5.dist-info/top_level.txt
corella_python-0.1.5.dist-info/RECORD
