Metadata-Version: 2.4
Name: corella-python
Version: 0.1.5
Summary: Package for creating Darwin Core Archives
Home-page: https://corella.ala.org.au/Python/
Author: Amanda Buyan
Author-email: amanda.buyan@csiro.au
License: MPL-2.0
Keywords: corella
Requires-Dist: pandas
Requires-Dist: beautifulsoup4
Requires-Dist: configparser
Requires-Dist: pytest
Requires-Dist: requests
Requires-Dist: shutils
Requires-Dist: tabulate
Dynamic: author
Dynamic: author-email
Dynamic: description
Dynamic: description-content-type
Dynamic: home-page
Dynamic: keywords
Dynamic: license
Dynamic: requires-dist
Dynamic: summary
